faux_lars-0.1.0.dist-info/METADATA
faux_lars-0.1.0.dist-info/WHEEL
faux_lars-0.1.0.dist-info/license_files/LICENSE
faux_lars/__init__.py
faux_lars/utils.py
faux_lars/faux_lars.abi3.so
faux_lars-0.1.0.dist-info/RECORD
